dcipher/__init__.py
dcipher/async_client.py
dcipher/client.py
dcipher/constants.py
dcipher/exceptions.py
dcipher/logger.py
dcipher-0.3.2.dist-info/LICENSE
dcipher-0.3.2.dist-info/METADATA
dcipher-0.3.2.dist-info/WHEEL
dcipher-0.3.2.dist-info/RECORD
