Metadata-Version: 2.1
Name: dcipher
Version: 0.3.2
Summary: The official Python client library for the Dcipher Workflows API
Home-page: https://github.com/kairosfuture/dcipher-workflows-api-python
License: MIT
Author: Dcipher Analytics AB
Author-email: dev@dcipheranalytics.com
Requires-Python: >=3.7,<4.0
Classifier: Intended Audience :: Developers
Classifier: License :: OSI Approved :: MIT License
Classifier: Operating System :: MacOS
Classifier: Operating System :: Microsoft :: Windows
Classifier: Operating System :: OS Independent
Classifier: Operating System :: POSIX
Classifier: Operating System :: POSIX :: Linux
Classifier: Programming Language :: Python :: 3
Classifier: Programming Language :: Python :: 3.7
Classifier: Programming Language :: Python :: 3.8
Classifier: Programming Language :: Python :: 3.9
Classifier: Programming Language :: Python :: 3.10
Classifier: Programming Language :: Python :: 3.11
Classifier: Programming Language :: Python :: 3.10
Classifier: Programming Language :: Python :: 3.11
Classifier: Programming Language :: Python :: 3.12
Classifier: Programming Language :: Python :: 3.7
Classifier: Programming Language :: Python :: 3.8
Classifier: Programming Language :: Python :: 3.9
Classifier: Topic :: Software Development :: Libraries :: Python Modules
Classifier: Typing :: Typed
Requires-Dist: httpx (>=0.23.0,<1)
Requires-Dist: requests (>=2.28.2,<3.0.0)
Requires-Dist: tenacity (>=8.2.3,<9.0.0)
Project-URL: Repository, https://github.com/kairosfuture/dcipher-workflows-api-python
